<?xml version="1.0" encoding="ISO-8859-1"?>
<departamentos>
<DEP_ROW Codigo='1'>
  <NOMBRE>CONTABILIDAD</NOMBRE>
  <LOCALIZACION>
	<PISO>2</PISO>
	<DESPACHO>3</DESPACHO>
  </LOCALIZACION>
</DEP_ROW>
<DEP_ROW Codigo='2'>
  <NOMBRE>INVESTIGACION</NOMBRE>
  <LOCALIZACION>
	<PISO>1</PISO>
	<DESPACHO>1</DESPACHO>
  </LOCALIZACION>
</DEP_ROW>
<DEP_ROW Codigo='3'>
  <NOMBRE>VENTAS</NOMBRE>
  <LOCALIZACION>
	<PISO>1</PISO>
	<DESPACHO>56</DESPACHO>
  </LOCALIZACION>
</DEP_ROW>
<DEP_ROW Codigo='4'>
  <NOMBRE>PRODUCCION</NOMBRE>
  <LOCALIZACION>
	<PISO>3</PISO>
	<DESPACHO>9</DESPACHO>
  </LOCALIZACION>
</DEP_ROW>
<DEP_ROW Codigo='5'>
  <NOMBRE>ADMINISTRACION</NOMBRE>
  <LOCALIZACION>
	<PISO>4</PISO>
	<DESPACHO>1</DESPACHO>
  </LOCALIZACION>
</DEP_ROW>
</departamentos>